{
    "picUrls": [
        "asset/image/avatar/notice/Notice_green_2.png",
        "asset/image/avatar/notice/Notice_green_3.png",
        "asset/image/avatar/notice/Notice_green_4.png",
        "asset/image/avatar/notice/Notice_green_5.png"
    ],
    "oriMode": 1,
    "autoFlip": true,
    "refObjs": {
        "1": {
            "y": -22,
            "x": -13,
            "height": 38,
            "width": 26,
            "radius": 20,
            "type": 0,
            "rotation": 0
        }
    },
    "helperSetting": {
        "1": {
            "mouseEventEnabledInEditor": true,
            "showOnEditor": true
        }
    },
    "helperType": 0,
    "referenceMode": false,
    "referenceID": 1,
    "parts": [
        {
            "id": 0,
            "showOnEditor": true,
            "mouseEventEnabledInEditor": true
        }
    ],
    "actionListArr": [
        {
            "id": 1,
            "frameImageInfo": [
                [
                    {
                        "picUrlIndex": 0,
                        "rect": [
                            0,
                            0,
                            32,
                            64
                        ],
                        "x": -16,
                        "y": -48,
                        "width": 32,
                        "height": 64,
                        "rotation": 0,
                        "alpha": 1,
                        "hue": 0,
                        "blur": 0,
                        "tonal_r": 0,
                        "tonal_g": 0,
                        "tonal_b": 0,
                        "tonal_gray": 0,
                        "tonal_mr": 1,
                        "tonal_mg": 1,
                        "tonal_mb": 1
                    },
                    {
                        "picUrlIndex": 1,
                        "rect": [
                            0,
                            0,
                            32,
                            64
                        ],
                        "x": -16,
                        "y": -48,
                        "width": 32,
                        "height": 64,
                        "rotation": 0,
                        "alpha": 1,
                        "hue": 0,
                        "blur": 0,
                        "tonal_r": 0,
                        "tonal_g": 0,
                        "tonal_b": 0,
                        "tonal_gray": 0,
                        "tonal_mr": 1,
                        "tonal_mg": 1,
                        "tonal_mb": 1
                    },
                    {
                        "picUrlIndex": 2,
                        "rect": [
                            0,
                            0,
                            32,
                            64
                        ],
                        "x": -16,
                        "y": -48,
                        "width": 32,
                        "height": 64,
                        "rotation": 0,
                        "alpha": 1,
                        "hue": 0,
                        "blur": 0,
                        "tonal_r": 0,
                        "tonal_g": 0,
                        "tonal_b": 0,
                        "tonal_gray": 0,
                        "tonal_mr": 1,
                        "tonal_mg": 1,
                        "tonal_mb": 1
                    },
                    {
                        "picUrlIndex": 3,
                        "rect": [
                            0,
                            0,
                            32,
                            64
                        ],
                        "x": -16,
                        "y": -48,
                        "width": 32,
                        "height": 64,
                        "rotation": 0,
                        "alpha": 1,
                        "hue": 0,
                        "blur": 0,
                        "tonal_r": 0,
                        "tonal_g": 0,
                        "tonal_b": 0,
                        "tonal_gray": 0,
                        "tonal_mr": 1,
                        "tonal_mg": 1,
                        "tonal_mb": 1
                    }
                ]
            ]
        }
    ],
    "id": 1071
}